{
  "draft": "draft-ietf-ecrit-mapping-arch-04",
  "doc_id": "RFC5582",
  "title": "Location-to-URL Mapping Architecture and Framework",
  "authors": [
    "H. Schulzrinne"
  ],
  "format": [
    "TEXT",
    "HTML"
  ],
  "page_count": "17",
  "pub_status": "INFORMATIONAL",
  "status": "INFORMATIONAL",
  "source": "Emergency Context Resolution with Internet Technologies",
  "abstract": "This document describes an architecture for a global, scalable, resilient, and administratively distributed system for mapping geographic location information to URLs, using the Location-to-Service Translation (LoST) protocol.  The architecture generalizes well-known approaches found in hierarchical lookup systems such as DNS.  This memo provides information for the Internet community.",
  "pub_date": "September 2009",
  "keywords": [
    "ECRIT",
    "Mapping",
    "LoST",
    "Emergency calling"
  ],
  "obsoletes": [],
  "obsoleted_by": [],
  "updates": [],
  "updated_by": [],
  "see_also": [],
  "doi": "10.17487/RFC5582",
  "errata_url": "https://www.rfc-editor.org/errata/rfc5582"
}