{
  "draft": "draft-kato-camellia-ctrccm-05",
  "doc_id": "RFC5528",
  "title": "Camellia Counter Mode and Camellia Counter with CBC-MAC Mode Algorithms",
  "authors": [
    "A. Kato",
    "M. Kanda",
    "S. Kanno"
  ],
  "format": [
    "TEXT",
    "HTML"
  ],
  "page_count": "22",
  "pub_status": "INFORMATIONAL",
  "status": "INFORMATIONAL",
  "source": "IETF - NON WORKING GROUP",
  "abstract": "This document describes the algorithms and presents test vectors for the Camellia block cipher algorithm in Counter mode (CTR) and Counter with Cipher Block Chaining MAC mode (CCM).  The purpose of this document is to make the Camellia-CTR and Camellia-CCM algorithm conveniently available to the Internet Community.  This memo provides information for the Internet community.",
  "pub_date": "April 2009",
  "keywords": [
    "Camellia",
    "Block Cipher",
    "Mode of operation"
  ],
  "obsoletes": [],
  "obsoleted_by": [],
  "updates": [],
  "updated_by": [],
  "see_also": [],
  "doi": "10.17487/RFC5528",
  "errata_url": null
}