{
  "draft": "draft-ietf-6man-ipv6-subnet-model-12",
  "doc_id": "RFC5942",
  "title": "IPv6 Subnet Model: The Relationship between Links and Subnet Prefixes",
  "authors": [
    "H. Singh",
    "W. Beebee",
    "E. Nordmark"
  ],
  "format": [
    "TEXT",
    "HTML"
  ],
  "page_count": "11",
  "pub_status": "PROPOSED STANDARD",
  "status": "PROPOSED STANDARD",
  "source": "IPv6 Maintenance",
  "abstract": "IPv6 specifies a model of a subnet that is different than the IPv4 subnet model.  The subtlety of the differences has resulted in incorrect implementations that do not interoperate.  This document spells out the most important difference: that an IPv6 address isn't automatically associated with an IPv6 on-link prefix.  This document also updates (partially due to security concerns caused by incorrect implementations) a part of the definition of \"on-link\" from RFC 4861. [STANDARDS-TRACK]",
  "pub_date": "July 2010",
  "keywords": [],
  "obsoletes": [],
  "obsoleted_by": [],
  "updates": [
    "RFC4861"
  ],
  "updated_by": [],
  "see_also": [],
  "doi": "10.17487/RFC5942",
  "errata_url": "https://www.rfc-editor.org/errata/rfc5942"
}