{
  "draft": "draft-irtf-p2prg-mythbustering-03",
  "doc_id": "RFC6821",
  "title": "Improving Peer Selection in Peer-to-peer Applications: Myths vs. Reality",
  "authors": [
    "E. Marocco",
    "A. Fusco",
    "I. Rimac",
    "V. Gurbani"
  ],
  "format": [
    "TEXT",
    "HTML"
  ],
  "page_count": "16",
  "pub_status": "INFORMATIONAL",
  "status": "INFORMATIONAL",
  "source": "Peer-to-Peer Research Group",
  "abstract": "Peer-to-peer (P2P) traffic optimization techniques that aim at improving locality in the peer selection process have attracted great interest in the research community and have been the subject of much discussion. Some of this discussion has produced controversial myths, some rooted in reality while others remain unfounded. This document evaluates the most prominent myths attributed to P2P optimization techniques by referencing the most relevant study or studies that have addressed facts pertaining to the myth. Using these studies, the authors hope to either confirm or refute each specific myth.\n\n This document is a product of the IRTF P2PRG (Peer-to-Peer Research Group).",
  "pub_date": "December 2012",
  "keywords": [
    "cross-domain traffic",
    "bandwidth",
    "transit traffic",
    "peer-to-peer caching",
    "peer-to-peer swarm"
  ],
  "obsoletes": [],
  "obsoleted_by": [],
  "updates": [],
  "updated_by": [],
  "see_also": [],
  "doi": "10.17487/RFC6821",
  "errata_url": null
}