{
  "draft": "draft-ietf-avt-rtp-rfc3984bis-12",
  "doc_id": "RFC6184",
  "title": "RTP Payload Format for H.264 Video",
  "authors": [
    "Y.-K. Wang",
    "R. Even",
    "T. Kristensen",
    "R. Jesup"
  ],
  "format": [
    "TEXT",
    "HTML"
  ],
  "page_count": "101",
  "pub_status": "PROPOSED STANDARD",
  "status": "PROPOSED STANDARD",
  "source": "Audio/Video Transport",
  "abstract": "This memo describes an RTP Payload format for the ITU-T Recommendation H.264 video codec and the technically identical ISO/IEC International Standard 14496-10 video codec, excluding the Scalable Video Coding (SVC) extension and the Multiview Video Coding extension, for which the RTP payload formats are defined elsewhere. The RTP payload format allows for packetization of one or more Network Abstraction Layer Units (NALUs), produced by an H.264 video encoder, in each RTP payload. The payload format has wide applicability, as it supports applications from simple low bitrate conversational usage, to Internet video streaming with interleaved transmission, to high bitrate video-on-demand.\n\n This memo obsoletes RFC 3984. Changes from RFC 3984 are summarized in Section 14. Issues on backward compatibility to RFC 3984 are discussed in Section 15. [STANDARDS-TRACK]",
  "pub_date": "May 2011",
  "keywords": [
    "AVC",
    "H.264/AVC",
    "Advanced Video Coding"
  ],
  "obsoletes": [
    "RFC3984"
  ],
  "obsoleted_by": [],
  "updates": [],
  "updated_by": [],
  "see_also": [],
  "doi": "10.17487/RFC6184",
  "errata_url": "https://www.rfc-editor.org/errata/rfc6184"
}