{
  "draft": "draft-ietf-ospf-prefix-hiding-07",
  "doc_id": "RFC6860",
  "title": "Hiding Transit-Only Networks in OSPF",
  "authors": [
    "Y. Yang",
    "A. Retana",
    "A. Roy"
  ],
  "format": [
    "TEXT",
    "HTML"
  ],
  "page_count": "13",
  "pub_status": "PROPOSED STANDARD",
  "status": "PROPOSED STANDARD",
  "source": "Open Shortest Path First IGP",
  "abstract": "A transit-only network is defined as a network connecting routers only. In OSPF, transit-only networks are usually configured with routable IP addresses, which are advertised in Link State Advertisements (LSAs) but are not needed for data traffic. In addition, remote attacks can be launched against routers by sending packets to these transit-only networks. This document presents a mechanism to hide transit-only networks to speed up network convergence and reduce vulnerability to remote attacks.\n\n In the context of this document, 'hiding' implies that the prefixes are not installed in the routing tables on OSPF routers. In some cases, IP addresses may still be visible when using OSPFv2.\n\n This document updates RFCs 2328 and 5340. [STANDARDS-TRACK]",
  "pub_date": "January 2013",
  "keywords": [],
  "obsoletes": [],
  "obsoleted_by": [],
  "updates": [
    "RFC2328",
    "RFC5340"
  ],
  "updated_by": [],
  "see_also": [],
  "doi": "10.17487/RFC6860",
  "errata_url": "https://www.rfc-editor.org/errata/rfc6860"
}