{
  "draft": null,
  "doc_id": "RFC608",
  "title": "Host names on-line",
  "authors": [
    "M.D. Kudlick"
  ],
  "format": [
    "TEXT",
    "HTML"
  ],
  "page_count": "4",
  "pub_status": "UNKNOWN",
  "status": "UNKNOWN",
  "source": "Legacy",
  "abstract": "Response to RFC 606; see also RFCs 627, 625 and 623.",
  "pub_date": "January 1974",
  "keywords": [],
  "obsoletes": [],
  "obsoleted_by": [
    "RFC810"
  ],
  "updates": [],
  "updated_by": [],
  "see_also": [],
  "doi": "10.17487/RFC608",
  "errata_url": null
}