{
  "draft": "draft-ietf-tsvwg-fecframe-ext-08",
  "doc_id": "RFC8680",
  "title": "Forward Error Correction (FEC) Framework Extension to Sliding Window Codes",
  "authors": [
    "V. Roca",
    "A. Begen"
  ],
  "format": [
    "XML",
    "TEXT",
    "HTML",
    "PDF"
  ],
  "page_count": "19",
  "pub_status": "PROPOSED STANDARD",
  "status": "PROPOSED STANDARD",
  "source": "Transport and Services Working Group",
  "abstract": "RFC 6363 describes a framework for using Forward Error Correction (FEC) codes to provide protection against packet loss.  The framework supports applying FEC to arbitrary packet flows over unreliable transport and is primarily intended for real-time, or streaming, media.  However, FECFRAME as per RFC 6363 is restricted to block FEC codes.  This document updates RFC 6363 to support FEC codes based on a sliding encoding window, in addition to block FEC codes, in a backward-compatible way.  During multicast/broadcast real-time content delivery, the use of sliding window codes significantly improves robustness in harsh environments, with less repair traffic and lower FEC-related added latency.",
  "pub_date": "January 2020",
  "keywords": [
    "FEC",
    "FECFRAME",
    "packet loss recovery",
    "RLC",
    "Sliding Window FEC Codes"
  ],
  "obsoletes": [],
  "obsoleted_by": [],
  "updates": [
    "RFC6363"
  ],
  "updated_by": [],
  "see_also": [],
  "doi": "10.17487/RFC8680",
  "errata_url": null
}