{
  "draft": "draft-ietf-opsawg-model-automation-framework-10",
  "doc_id": "RFC8969",
  "title": "A Framework for Automating Service and Network Management with YANG",
  "authors": [
    "Q. Wu, Ed.",
    "M. Boucadair, Ed.",
    "D. Lopez",
    "C. Xie",
    "L. Geng"
  ],
  "format": [
    "XML",
    "TEXT",
    "HTML",
    "PDF"
  ],
  "page_count": "40",
  "pub_status": "INFORMATIONAL",
  "status": "INFORMATIONAL",
  "source": "Operations and Management Area Working Group",
  "abstract": "Data models provide a programmatic approach to represent services and networks. Concretely, they can be used to derive configuration information for network and service components, and state information that will be monitored and tracked. Data models can be used during the service and network management life cycle (e.g., service instantiation, service provisioning, service optimization, service monitoring, service diagnosing, and service assurance). Data models are also instrumental in the automation of network management, and they can provide closed-loop control for adaptive and deterministic service creation, delivery, and maintenance.\n\n This document describes a framework for service and network management automation that takes advantage of YANG modeling technologies. This framework is drawn from a network operator perspective irrespective of the origin of a data model; thus, it can accommodate YANG modules that are developed outside the IETF.",
  "pub_date": "January 2021",
  "keywords": [
    "Model Driven",
    "YANG Data Model",
    "automation",
    "service delivery",
    "notification",
    "SDN"
  ],
  "obsoletes": [],
  "obsoleted_by": [],
  "updates": [],
  "updated_by": [],
  "see_also": [],
  "doi": "10.17487/RFC8969",
  "errata_url": "https://www.rfc-editor.org/errata/rfc8969"
}