{
  "draft": null,
  "doc_id": "RFC820",
  "title": "Assigned numbers",
  "authors": [
    "J. Postel"
  ],
  "format": [
    "TEXT",
    "HTML"
  ],
  "page_count": "22",
  "pub_status": "UNKNOWN",
  "status": "HISTORIC",
  "source": "Legacy",
  "abstract": "This RFC is an old version, see RFC 870.",
  "pub_date": "August 1982",
  "keywords": [],
  "obsoletes": [
    "RFC790"
  ],
  "obsoleted_by": [
    "RFC870"
  ],
  "updates": [],
  "updated_by": [],
  "see_also": [],
  "doi": "10.17487/RFC820",
  "errata_url": null
}