{
  "draft": "draft-ietf-rtgwg-lne-model-10",
  "doc_id": "RFC8530",
  "title": "YANG Model for Logical Network Elements",
  "authors": [
    "L. Berger",
    "C. Hopps",
    "A. Lindem",
    "D. Bogdanovic",
    "X. Liu"
  ],
  "format": [
    "TEXT",
    "HTML"
  ],
  "page_count": "49",
  "pub_status": "PROPOSED STANDARD",
  "status": "PROPOSED STANDARD",
  "source": "Routing Area Working Group",
  "abstract": "This document defines a logical network element (LNE) YANG module that is compliant with the Network Management Datastore Architecture (NMDA).  This module can be used to manage the logical resource partitioning that may be present on a network device.  Examples of common industry terms for logical resource partitioning are logical systems or logical routers.  The YANG model in this document conforms with NMDA as defined in RFC 8342.",
  "pub_date": "March 2019",
  "keywords": [
    "VRF",
    "VSI",
    "VPN"
  ],
  "obsoletes": [],
  "obsoleted_by": [],
  "updates": [],
  "updated_by": [],
  "see_also": [],
  "doi": "10.17487/RFC8530",
  "errata_url": null
}