{
  "draft": "draft-ietf-cdni-delegation-acme-05",
  "doc_id": "RFC9538",
  "title": "Content Delivery Network Interconnection (CDNI) Delegation Using the Automated Certificate Management Environment",
  "authors": [
    "F. Fieau, Ed.",
    "E. Stephan",
    "S. Mishra"
  ],
  "format": [
    "XML",
    "TEXT",
    "HTML",
    "PDF"
  ],
  "page_count": "10",
  "pub_status": "PROPOSED STANDARD",
  "status": "PROPOSED STANDARD",
  "source": "Content Delivery Networks Interconnection",
  "abstract": "This document defines metadata to support delegating the delivery of HTTPS content between two or more interconnected Content Delivery Networks (CDNs).  Specifically, this document defines a Content Delivery Network Interconnection (CDNI) Metadata interface object to enable delegation of X.509 certificates leveraging delegation schemes defined in RFC 9115.  Per RFC 9115, delegating entities can remain in full control of the delegation and can revoke it at any time.  This avoids the need to share private cryptographic key material between the involved entities.",
  "pub_date": "February 2024",
  "keywords": [
    "HTTPS",
    "delegation",
    "ACME",
    "STAR"
  ],
  "obsoletes": [],
  "obsoleted_by": [],
  "updates": [],
  "updated_by": [],
  "see_also": [],
  "doi": "10.17487/RFC9538",
  "errata_url": null
}