{"draft":"draft-ietf-ntp-update-registries-16","doc_id":"RFC9748","title":"Updating the NTP Registries","authors":["R. Salz"],"format":["HTML","TEXT","PDF","XML"],"page_count":"10","pub_status":"PROPOSED STANDARD","status":"PROPOSED STANDARD","source":"Network Time Protocols","abstract":"The Network Time Protocol (NTP) and Network Time Security (NTS)\r\ndocuments define a number of registries, collectively called the NTP\r\nregistries.\r\n\r\nSome registries are correct, but some include incorrect assignments\r\nand some don't follow common practice. For the sake of completeness,\r\nthis document reviews all NTP and NTS registries, and corrects the\r\nregistries where necessary.\r\n\r\nThis document updates RFCs 5905, 5906, 7821, 7822, and 8573.","pub_date":"February 2025","keywords":["NTP","extensions","registries","IANA"],"obsoletes":[],"obsoleted_by":[],"updates":["RFC5905","RFC5906","RFC7821","RFC7822","RFC8573"],"updated_by":[],"see_also":[],"doi":"10.17487\/RFC9748","errata_url":null}