{"draft":"draft-ietf-httpbis-digest-headers-13","doc_id":"RFC9530","title":"Digest Fields","authors":["R. Polli","L. Pardue"],"format":["HTML","TEXT","PDF","XML"],"page_count":"32","pub_status":"PROPOSED STANDARD","status":"PROPOSED STANDARD","source":"HTTP","abstract":"This document defines HTTP fields that support integrity digests.\r\nThe Content-Digest field can be used for the integrity of HTTP\r\nmessage content.  The Repr-Digest field can be used for the integrity\r\nof HTTP representations.  Want-Content-Digest and Want-Repr-Digest\r\ncan be used to indicate a sender's interest and preferences for\r\nreceiving the respective Integrity fields.\r\n\r\nThis document obsoletes RFC 3230 and the Digest and Want-Digest HTTP\r\nfields.","pub_date":"February 2024","keywords":["Digest"],"obsoletes":["RFC3230"],"obsoleted_by":[],"updates":[],"updated_by":[],"see_also":[],"doi":"10.17487\/RFC9530","errata_url":null}